{
  "schema_version": "business_reading.slot_mapping.compat.v2",
  "generated_at": "2026-06-17T18:26:35",
  "source": "structured_business_model.json",
  "mappings": [
    {
      "id": "CONFIG_001",
      "stage": "config_constraint",
      "fact_ids": [
        "FACT_0002"
      ],
      "evidence_refs": [
        "EVD_0001"
      ]
    },
    {
      "id": "STEP_001",
      "stage": "state_change",
      "fact_ids": [
        "FACT_0004"
      ],
      "evidence_refs": [
        "EVD_0001"
      ]
    }
  ]
}
